equsolver/__init__.py
equsolver/solver.py
equsolver-0.1.0.dist-info/METADATA
equsolver-0.1.0.dist-info/WHEEL
equsolver-0.1.0.dist-info/top_level.txt
equsolver-0.1.0.dist-info/RECORD
