Metadata-Version: 2.4
Name: equsolver
Version: 0.1.0
Summary: Lightweight symbolic solver for equations
Author: kkyian
Dynamic: author
Dynamic: summary
